lovely_numpy/__init__.py
lovely_numpy/_modidx.py
lovely_numpy/lo.py
lovely_numpy/repr_chans.py
lovely_numpy/repr_plt.py
lovely_numpy/repr_rgb.py
lovely_numpy/repr_str.py
lovely_numpy/utils/__init__.py
lovely_numpy/utils/colormap.py
lovely_numpy/utils/config.py
lovely_numpy/utils/pad.py
lovely_numpy/utils/tile2d.py
lovely_numpy/utils/utils.py
lovely_numpy-0.2.18.dist-info/licenses/LICENSE
lovely_numpy-0.2.18.dist-info/METADATA
lovely_numpy-0.2.18.dist-info/WHEEL
lovely_numpy-0.2.18.dist-info/entry_points.txt
lovely_numpy-0.2.18.dist-info/top_level.txt
lovely_numpy-0.2.18.dist-info/RECORD
