Metadata-Version: 2.4
Name: lovely-numpy
Version: 0.2.18
Summary: 💟 Lovely numpy
Home-page: https://github.com/xl0/lovely-numpy
Author: Alexey Zaytsev
Author-email: alexey.zaytsev@gmail.com
License: MIT License
Project-URL: Documentation, https://xl0.github.io/lovely-numpy
Keywords: jupyter numpy visualisation
Classifier: Development Status :: 3 - Alpha
Classifier: Intended Audience :: Developers
Classifier: Natural Language :: English
Classifier: Programming Language :: Python :: 3.7
Classifier: Programming Language :: Python :: 3.8
Classifier: Programming Language :: Python :: 3.9
Classifier: Programming Language :: Python :: 3.10
Classifier: Programming Language :: Python :: 3.12
Classifier: Programming Language :: Python :: 3.13
Classifier: License :: OSI Approved :: MIT License
Requires-Python: >=3.7
License-File: LICENSE
Requires-Dist: packaging
Requires-Dist: numpy>=1.17
Requires-Dist: fastcore
Requires-Dist: matplotlib
Provides-Extra: dev
Requires-Dist: scipy; extra == "dev"
Requires-Dist: ipython; extra == "dev"
Dynamic: author
Dynamic: author-email
Dynamic: classifier
Dynamic: description
Dynamic: description-content-type
Dynamic: home-page
Dynamic: keywords
Dynamic: license
Dynamic: license-file
Dynamic: project-url
Dynamic: provides-extra
Dynamic: requires-dist
Dynamic: requires-python
Dynamic: summary
